Metadata-Version: 2.1
Name: robotframework-importresource
Version: 0.2.0
Summary: Tool to import robotframework resource files from python packages
Home-page: https://github.com/rasjani/robotframework-importresource
Author: Jani Mikkonen
Author-email: jani.mikkonen@gmail.com
License: Apache License 2.0
Keywords: robot framework testing automation
Platform: any
Classifier: Development Status :: 3 - Alpha
Classifier: Topic :: Software Development :: Testing
Classifier: Operating System :: OS Independent
Classifier: License :: OSI Approved :: Apache Software License
Classifier: Programming Language :: Python
Classifier: Programming Language :: Python :: 3
Classifier: Programming Language :: Python :: 3.6
Classifier: Programming Language :: Python :: 3.7
Classifier: Topic :: Software Development :: Testing
Classifier: Framework :: Robot Framework
Classifier: Framework :: Robot Framework :: Library
